octo_pipeline_python/backends/cfn_nag/__init__.py
octo_pipeline_python/backends/cfn_nag/cfn_nag_backend.py
octo_pipeline_python/backends/cfn_nag/actions/__init__.py
octo_pipeline_python/backends/cfn_nag/actions/cfn_nag_security_checks.py
octo_pipeline_python/backends/cfn_nag/models/__init__.py
octo_pipeline_python/backends/cfn_nag/models/cfn_nag_model.py
octo_pipeline_python/backends/cfn_nag/profiles/default.profile
octo_pipeline_backend_cfn_nag_python-1.3.2.dist-info/LICENSE.txt
octo_pipeline_backend_cfn_nag_python-1.3.2.dist-info/METADATA
octo_pipeline_backend_cfn_nag_python-1.3.2.dist-info/README.md
octo_pipeline_backend_cfn_nag_python-1.3.2.dist-info/WHEEL
octo_pipeline_backend_cfn_nag_python-1.3.2.dist-info/top_level.txt
octo_pipeline_backend_cfn_nag_python-1.3.2.dist-info/RECORD
